zrm/__init__.py
zrm/actions/examples_pb2.py
zrm/actions/examples_pb2.pyi
zrm/cli/action.py
zrm/cli/node.py
zrm/cli/proto.py
zrm/cli/service.py
zrm/cli/topic.py
zrm/msgs/geometry_pb2.py
zrm/msgs/geometry_pb2.pyi
zrm/msgs/header_pb2.py
zrm/msgs/header_pb2.pyi
zrm/msgs/sensor_pb2.py
zrm/msgs/sensor_pb2.pyi
zrm/msgs/vision_pb2.py
zrm/msgs/vision_pb2.pyi
zrm/proto/actions/examples.proto
zrm/proto/msgs/geometry.proto
zrm/proto/msgs/header.proto
zrm/proto/msgs/sensor.proto
zrm/proto/msgs/vision.proto
zrm/proto/srvs/examples.proto
zrm/proto/srvs/std.proto
zrm/srvs/examples_pb2.py
zrm/srvs/examples_pb2.pyi
zrm/srvs/std_pb2.py
zrm/srvs/std_pb2.pyi
zrm-2.1.0.dist-info/WHEEL
zrm-2.1.0.dist-info/entry_points.txt
zrm-2.1.0.dist-info/METADATA
zrm-2.1.0.dist-info/RECORD
