Metadata-Version: 2.3
Name: zrm
Version: 2.1.0
Summary: A minimal, single-file communication middleware built on Zenoh
Author: JafarAbdi
Author-email: JafarAbdi <jafar.uruc@gmail.com>
License: BSD 3-Clause License
Classifier: Development Status :: 4 - Beta
Classifier: Intended Audience :: Developers
Classifier: Programming Language :: Python :: 3
Classifier: Programming Language :: Python :: 3.10
Classifier: Programming Language :: Python :: 3.11
Classifier: Programming Language :: Python :: 3.12
Classifier: Programming Language :: Python :: 3.13
Classifier: Topic :: Software Development :: Libraries :: Python Modules
Classifier: Topic :: System :: Networking
Requires-Dist: eclipse-zenoh>=1.6.2
Requires-Dist: protobuf>=6.33.0
Requires-Python: >=3.10
Project-URL: CI, https://github.com/JafarAbdi/zrm/actions
Project-URL: Homepage, https://github.com/JafarAbdi/zrm
Project-URL: Issues, https://github.com/JafarAbdi/zrm/issues
Project-URL: Repository, https://github.com/JafarAbdi/zrm
